pyogmios_client/__init__.py
pyogmios_client/connection.py
pyogmios_client/enums/__init__.py
pyogmios_client/exceptions.py
pyogmios_client/models/__init__.py
pyogmios_client/models/base_model.py
pyogmios_client/models/base_request_response_model.py
pyogmios_client/models/request_model.py
pyogmios_client/models/response_model.py
pyogmios_client/models/result_models.py
pyogmios_client/models/server_health_model.py
pyogmios_client/ouroboros_mini_protocols/__init__.py
pyogmios_client/ouroboros_mini_protocols/chain_sync/__init__.py
pyogmios_client/ouroboros_mini_protocols/chain_sync/chain_sync_client.py
pyogmios_client/ouroboros_mini_protocols/chain_sync/find_intersect.py
pyogmios_client/ouroboros_mini_protocols/chain_sync/request_next.py
pyogmios_client/ouroboros_mini_protocols/state_query/__init__.py
pyogmios_client/ouroboros_mini_protocols/state_query/queries/__init__.py
pyogmios_client/ouroboros_mini_protocols/state_query/queries/block_height.py
pyogmios_client/ouroboros_mini_protocols/state_query/queries/chain_tip.py
pyogmios_client/ouroboros_mini_protocols/state_query/queries/current_epoch.py
pyogmios_client/ouroboros_mini_protocols/state_query/queries/current_protocol_parameters.py
pyogmios_client/ouroboros_mini_protocols/state_query/queries/delegations_and_rewards.py
pyogmios_client/ouroboros_mini_protocols/state_query/queries/era_start.py
pyogmios_client/ouroboros_mini_protocols/state_query/queries/era_summaries.py
pyogmios_client/ouroboros_mini_protocols/state_query/queries/genesis_config.py
pyogmios_client/ouroboros_mini_protocols/state_query/queries/ledger_tip.py
pyogmios_client/ouroboros_mini_protocols/state_query/queries/non_myopic_member_rewards.py
pyogmios_client/ouroboros_mini_protocols/state_query/queries/pool_ids.py
pyogmios_client/ouroboros_mini_protocols/state_query/queries/pool_parameters.py
pyogmios_client/ouroboros_mini_protocols/state_query/queries/pools_ranking.py
pyogmios-0.7.4.dist-info/LICENSE
pyogmios-0.7.4.dist-info/METADATA
pyogmios-0.7.4.dist-info/WHEEL
pyogmios-0.7.4.dist-info/RECORD
