Metadata-Version: 2.1
Name: pyogmios
Version: 0.7.4
Summary: Python client for Ogmios
Author: Hareem Adderley
Author-email: hadderley@kingpinapps.com
Requires-Python: >=3.8.10,<3.12
Classifier: Development Status :: 4 - Beta
Classifier: License :: OSI Approved :: Apache Software License
Classifier: Operating System :: OS Independent
Classifier: Programming Language :: Python :: 3
Classifier: Programming Language :: Python :: 3.9
Classifier: Programming Language :: Python :: 3.10
Classifier: Programming Language :: Python :: 3.11
Classifier: Programming Language :: Python :: 3
Requires-Dist: aiodns (>=3.1.1,<4.0.0)
Requires-Dist: aiohttp (>=3.9.0,<4.0.0)
Requires-Dist: nanoid (>=2.0.0,<3.0.0)
Requires-Dist: promise (>=2.3,<3.0)
Requires-Dist: pydantic (>=2.5.1,<3.0.0)
Requires-Dist: pyee (>=11.0.1,<12.0.0)
Requires-Dist: rel (>=0.4.9,<0.5.0)
Requires-Dist: requests (>=2.31.0,<3.0.0)
Requires-Dist: websocket-client (>=1.6.4,<2.0.0)
